play.py
chess_2d/__init__.py
chess_2d/__main__.py
chess_2d/Board/build.py
chess_2d/Game_Engine/runner.py
chess_2d/Game_Engine/static_variables.py
chess_2d/Game_Engine/Error_handler/error_printer.py
chess_2d/Game_Engine/Error_handler/set_error.py
chess_2d/Game_Engine/Game_Rules/game_rules.py
chess_2d/Game_Engine/Game_Rules/move_validator.py
chess_2d/Game_Engine/Game_Rules/possible_position.py
chess_2d/Game_Engine/Game_utils/board_printing.py
chess_2d/Game_Engine/Game_utils/common_functions.py
chess_2d/Game_Engine/Game_utils/perform_move.py
chess_2d/Game_Engine/Game_utils/user_input_handling.py
chess_2d/Game_Engine/Game_utils/util.py
chess_2d/img/black_bishop.png
chess_2d/img/black_king.png
chess_2d/img/black_knight.png
chess_2d/img/black_pawn.png
chess_2d/img/black_queen.png
chess_2d/img/black_rook.png
chess_2d/img/white_bishop.png
chess_2d/img/white_king.png
chess_2d/img/white_knight.png
chess_2d/img/white_pawn.png
chess_2d/img/white_queen.png
chess_2d/img/white_rook.png
kesav_chess_2d-1.1.0.dist-info/licenses/LICENSE
kesav_chess_2d-1.1.0.dist-info/METADATA
kesav_chess_2d-1.1.0.dist-info/WHEEL
kesav_chess_2d-1.1.0.dist-info/entry_points.txt
kesav_chess_2d-1.1.0.dist-info/top_level.txt
kesav_chess_2d-1.1.0.dist-info/RECORD
