Metadata-Version: 2.4
Name: kesav-chess-2d
Version: 1.1.0
Summary: A 2D chess game with GUI
Author-email: sai kesav <saikesav67254@gmail.com>
Project-URL: Homepage, https://github.com/saikesav-sai/chess_2d
Keywords: chess,game,chess-2d
Classifier: License :: OSI Approved :: GNU General Public License v3 (GPLv3)
Classifier: Programming Language :: Python
Classifier: Programming Language :: Python :: 3
Requires-Python: >=3.9
License-File: LICENSE
Dynamic: license-file
